zlmdb/__init__.py
zlmdb/_database.py
zlmdb/_errors.py
zlmdb/_meta.py
zlmdb/_pmap.py
zlmdb/_schema.py
zlmdb/_transaction.py
zlmdb/_types.py
zlmdb/_version.py
zlmdb/cli.py
zlmdb/_flatc/__init__.py
zlmdb/_lmdb_vendor/__init__.py
zlmdb/_lmdb_vendor/__main__.py
zlmdb/_lmdb_vendor/_config.py
zlmdb/_lmdb_vendor/cffi.py
zlmdb/_lmdb_vendor/tool.py
zlmdb/flatbuffers/__init__.py
zlmdb/flatbuffers/_git_version.py
zlmdb/flatbuffers/_version.py
zlmdb/flatbuffers/builder.py
zlmdb/flatbuffers/compat.py
zlmdb/flatbuffers/encode.py
zlmdb/flatbuffers/flexbuffers.py
zlmdb/flatbuffers/number_types.py
zlmdb/flatbuffers/packer.py
zlmdb/flatbuffers/reflection.fbs
zlmdb/flatbuffers/table.py
zlmdb/flatbuffers/util.py
zlmdb/flatbuffers/reflection/AdvancedFeatures.py
zlmdb/flatbuffers/reflection/BaseType.py
zlmdb/flatbuffers/reflection/Enum.py
zlmdb/flatbuffers/reflection/EnumVal.py
zlmdb/flatbuffers/reflection/Field.py
zlmdb/flatbuffers/reflection/KeyValue.py
zlmdb/flatbuffers/reflection/Object.py
zlmdb/flatbuffers/reflection/RPCCall.py
zlmdb/flatbuffers/reflection/Schema.py
zlmdb/flatbuffers/reflection/SchemaFile.py
zlmdb/flatbuffers/reflection/Service.py
zlmdb/flatbuffers/reflection/Type.py
zlmdb/flatbuffers/reflection/__init__.py
zlmdb/tests/conftest.py
zlmdb/tests/lmdb/__init__.py
zlmdb/tests/lmdb/address_book.py
zlmdb/tests/lmdb/crash_test.py
zlmdb/tests/lmdb/cursor_test.py
zlmdb/tests/lmdb/env_test.py
zlmdb/tests/lmdb/getmulti_test.py
zlmdb/tests/lmdb/iteration_test.py
zlmdb/tests/lmdb/package_test.py
zlmdb/tests/lmdb/test_lmdb.py
zlmdb/tests/lmdb/testlib.py
zlmdb/tests/lmdb/tool_test.py
zlmdb/tests/lmdb/txn_test.py
zlmdb/tests/orm/MNodeLog.py
zlmdb/tests/orm/__init__.py
zlmdb/tests/orm/_schema_fbs.py
zlmdb/tests/orm/_schema_mnode_log.py
zlmdb/tests/orm/_schema_py2.py
zlmdb/tests/orm/_schema_py3.py
zlmdb/tests/orm/_test_flatbuffers.py
zlmdb/tests/orm/_test_serialization.py
zlmdb/tests/orm/test_basic.py
zlmdb/tests/orm/test_etcd.py
zlmdb/tests/orm/test_pmap_indexes.py
zlmdb-25.12.3.dist-info/METADATA
zlmdb-25.12.3.dist-info/WHEEL
zlmdb-25.12.3.dist-info/entry_points.txt
zlmdb-25.12.3.dist-info/licenses/LICENSE
zlmdb-25.12.3.dist-info/licenses/NOTICE
zlmdb-25.12.3.dist-info/RECORD
