Metadata-Version: 2.4
Name: zlmdb
Version: 25.12.3
Summary: Object-relational zero-copy in-memory database layer for LMDB
Project-URL: Homepage, https://github.com/crossbario/zlmdb
Project-URL: Documentation, https://zlmdb.readthedocs.io
Project-URL: Repository, https://github.com/crossbario/zlmdb
Project-URL: Changelog, https://github.com/crossbario/zlmdb/blob/master/docs/changelog.rst
Author-email: typedef int GmbH <contact@typedefint.eu>
License-Expression: MIT
License-File: LICENSE
License-File: NOTICE
Keywords: cbor,crossbar,database,embedded,flatbuffers,key-value,lmdb,wamp,zero-copy,zlmdb
Classifier: Development Status :: 5 - Production/Stable
Classifier: Intended Audience :: Developers
Classifier: Natural Language :: English
Classifier: Operating System :: OS Independent
Classifier: Programming Language :: Python
Classifier: Programming Language :: Python :: 3
Classifier: Programming Language :: Python :: 3.11
Classifier: Programming Language :: Python :: 3.12
Classifier: Programming Language :: Python :: 3.13
Classifier: Programming Language :: Python :: 3.14
Classifier: Programming Language :: Python :: Implementation :: CPython
Classifier: Programming Language :: Python :: Implementation :: PyPy
Classifier: Topic :: Database
Classifier: Topic :: Database :: Database Engines/Servers
Classifier: Topic :: Software Development :: Libraries
Classifier: Topic :: Software Development :: Libraries :: Python Modules
Requires-Python: >=3.11
Requires-Dist: cbor2>=5.4.6
Requires-Dist: cffi>=1.15.1
Requires-Dist: click>=8.1.3
Requires-Dist: numpy>=1.24.1
Requires-Dist: pynacl>=1.5.0
Requires-Dist: pyyaml>=6.0
Requires-Dist: setuptools>=40.8.0
Requires-Dist: txaio>=25.12.2
Provides-Extra: dev
Requires-Dist: auditwheel>=5.0.0; extra == 'dev'
Requires-Dist: build>=1.0.0; extra == 'dev'
Requires-Dist: coverage>=5.0.0; extra == 'dev'
Requires-Dist: pyenchant>=3.0.0; extra == 'dev'
Requires-Dist: pytest-runner>=2.11.1; extra == 'dev'
Requires-Dist: pytest>=3.4.2; extra == 'dev'
Requires-Dist: ruff>=0.1.0; extra == 'dev'
Requires-Dist: scour>=0.38; extra == 'dev'
Requires-Dist: sphinx-autoapi>=2.0.0; extra == 'dev'
Requires-Dist: sphinx-rtd-theme>=0.1.9; extra == 'dev'
Requires-Dist: sphinx>=1.7.1; extra == 'dev'
Requires-Dist: sphinxcontrib-images>=0.9.0; extra == 'dev'
Requires-Dist: sphinxcontrib-spelling>=7.0.0; extra == 'dev'
Requires-Dist: twine>=3.3.0; extra == 'dev'
Requires-Dist: twisted>=20.3.0; extra == 'dev'
Requires-Dist: wheel>=0.36.2; extra == 'dev'
Provides-Extra: docs
Requires-Dist: furo>=2024.7.0; extra == 'docs'
Requires-Dist: linkify-it-py>=2.0.0; extra == 'docs'
Requires-Dist: myst-parser>=2.0; extra == 'docs'
Requires-Dist: pyenchant>=3.2; extra == 'docs'
Requires-Dist: scour>=0.38; extra == 'docs'
Requires-Dist: sphinx-autoapi>=2.1.0; extra == 'docs'
Requires-Dist: sphinx-copybutton>=0.5; extra == 'docs'
Requires-Dist: sphinx-design>=0.5; extra == 'docs'
Requires-Dist: sphinx>=8.2.3; extra == 'docs'
Requires-Dist: sphinxcontrib-images>=0.9; extra == 'docs'
Requires-Dist: sphinxcontrib-spelling>=8.0; extra == 'docs'
Requires-Dist: sphinxext-opengraph>=0.9; extra == 'docs'
